odoo/addons/shopinvader_filtered_model/README.rst
odoo/addons/shopinvader_filtered_model/__init__.py
odoo/addons/shopinvader_filtered_model/__manifest__.py
odoo/addons/shopinvader_filtered_model/utils.py
odoo/addons/shopinvader_filtered_model/i18n/shopinvader_filtered_model.pot
odoo/addons/shopinvader_filtered_model/readme/CONTRIBUTORS.rst
odoo/addons/shopinvader_filtered_model/readme/DESCRIPTION.rst
odoo/addons/shopinvader_filtered_model/static/description/index.html
odoo_addon_shopinvader_filtered_model-16.0.1.1.1.dist-info/METADATA
odoo_addon_shopinvader_filtered_model-16.0.1.1.1.dist-info/WHEEL
odoo_addon_shopinvader_filtered_model-16.0.1.1.1.dist-info/top_level.txt
odoo_addon_shopinvader_filtered_model-16.0.1.1.1.dist-info/RECORD
